{
    "root": {
        "attribute": "odor",
        "predicateName": "==",
        "pivot": "n",
        "match": {
            "attribute": "spore-print-color",
            "predicateName": "==",
            "pivot": "r",
            "match": {
                "category": "p"
            },
            "notMatch": {
                "attribute": "cap-color",
                "predicateName": "==",
                "pivot": "y",
                "match": {
                    "category": "p"
                },
                "notMatch": {
                    "attribute": "spore-print-color",
                    "predicateName": "==",
                    "pivot": "w",
                    "match": {
                        "attribute": "habitat",
                        "predicateName": "==",
                        "pivot": "d",
                        "match": {
                            "attribute": "ring-type",
                            "predicateName": "==",
                            "pivot": "e",
                            "match": {
                                "category": "p"
                            },
                            "notMatch": {
                                "category": "e"
                            },
                            "matchedCount": 11,
                            "notMatchedCount": 4
                        },
                        "notMatch": {
                            "attribute": "habitat",
                            "predicateName": "==",
                            "pivot": "l",
                            "match": {
                                "attribute": "cap-color",
                                "predicateName": "==",
                                "pivot": "w",
                                "match": {
                                    "category": "p"
                                },
                                "notMatch": {
                                    "category": "e"
                                },
                                "matchedCount": 5,
                                "notMatchedCount": 33
                            },
                            "notMatch": {
                                "category": "e"
                            },
                            "matchedCount": 38,
                            "notMatchedCount": 278
                        },
                        "matchedCount": 15,
                        "notMatchedCount": 316
                    },
                    "notMatch": {
                        "category": "e"
                    },
                    "matchedCount": 331,
                    "notMatchedCount": 1668
                },
                "matchedCount": 14,
                "notMatchedCount": 1999
            },
            "matchedCount": 49,
            "notMatchedCount": 2013
        },
        "notMatch": {
            "attribute": "ring-type",
            "predicateName": "==",
            "pivot": "p",
            "match": {
                "attribute": "odor",
                "predicateName": "==",
                "pivot": "l",
                "match": {
                    "category": "e"
                },
                "notMatch": {
                    "category": "p"
                },
                "matchedCount": 259,
                "notMatchedCount": 742
            },
            "notMatch": {
                "category": "p"
            },
            "matchedCount": 1001,
            "notMatchedCount": 1811
        },
        "matchedCount": 2062,
        "notMatchedCount": 2812
    }
}